moshpdf/__init__.py
moshpdf/pdf2image.py
moshpdf/pdf2text.py
wesamhamed-1.0.dist-info/LICENSE
wesamhamed-1.0.dist-info/METADATA
wesamhamed-1.0.dist-info/WHEEL
wesamhamed-1.0.dist-info/top_level.txt
wesamhamed-1.0.dist-info/RECORD
