Metadata-Version: 2.1
Name: wesamhamed
Version: 1.0
Summary: This is the home of our project.
Home-page: UNKNOWN
Author: wesam hamed
Author-email: UNKNOWN
License: UNKNOWN
Platform: UNKNOWN
